Codigos/comparadores/igual/igual.v
//comparador igual

module igual(
   input [2:0] A,
   input [2:0] B,
   output F
);

assign F=(A==B);

endmodule

Codigos/comparadores/igual/estimulos_igual.v
`timescale 1ns / 10 ps
module estimulos_igual ();
//********************************
//declaracion de variables para conexion
 reg [2:0]A;
 reg [2:0]B;
 wire F;
//********************************
//conexion del circuito
igual S1(
.A(A),
.B(B),
.F(F)
);
//*********************************
//estimulos
initial begin
  A=3'b000; B=3'b000;   #20;
  A=3'b001; B=3'b001;   #20;
  A=3'b010; B=3'b010;   #20;
  A=3'b011; B=3'b011;   #20;
  A=3'b100; B=3'b100;   #20;
  A=3'b101; B=3'b101;   #20;
  A=3'b100; B=3'b101;   #20;
  A=3'b011; B=3'b000;   #20;
  $finish;
end
//************************************
//mostrar resultados con gtkwave
initial begin
  $dumpfile("ARCHIVO.vcd");
  $dumpvars;
end
//**********************************
//mostrar resultados en consola
initial begin
$display("---------|---|");
$display("  A   B  | F |");
$display("---------|---|");
$monitor(" %b %b | %b |",A,B,F);
end

endmodule

Codigos/comparadores/igual/ARCHIVO.vcd
$date
	Sun Jan 17 15:33:45 2021
$end
$version
	Icarus Verilog
$end
$timescale
	10ps
$end
$scope module estimulos_igual $end
$var wire 1 ! F $end
$var reg 3 " A [2:0] $end
$var reg 3 # B [2:0] $end
$scope module S1 $end
$var wire 3 $ A [2:0] $end
$var wire 3 % B [2:0] $end
$var wire 1 ! F $end
$upscope $end
$upscope $end
$enddefinitions $end
#0
$dumpvars
b0 %
b0 $
b0 #
b0 "
1!
$end
#2000
b1 #
b1 %
1!
b1 "
b1 $
#4000
b10 #
b10 %
1!
b10 "
b10 $
#6000
b11 #
b11 %
1!
b11 "
b11 $
#8000
b100 #
b100 %
1!
b100 "
b100 $
#10000
b101 #
b101 %
1!
b101 "
b101 $
#12000
0!
b100 "
b100 $
#14000
b0 #
b0 %
b11 "
b11 $
