Laboratorios/punto5/sop_pos/punto5_pos_sop.v
module punto5_pos_sop(
//entradas y salidas
//modo tipo ancho nombre
 input A,B,C,
 output Fsimp,Fpos,Fsop,
 output reg Fcase
);
assign Fsimp=(A & ~B)|(~B & C)|(A & C);
assign Fpos=(A|B|C)&(A|~B|C)&(A|~B|~C)&(~A|~B|C);
assign Fsop=(~A&~B&C)|(A&~B&~C)|(A&~B&C)|(A&B&C);
always @(*)
     case ({A,B,C})
	      3'd0: Fcase = 1'b0;
		  3'd1: Fcase = 1'b1;
		  3'd2: Fcase = 1'b0;
		  3'd3: Fcase = 1'b0;
		  3'd4: Fcase = 1'b1;
		  3'd5: Fcase = 1'b1;
		  3'd6: Fcase = 1'b0;
		  3'd7: Fcase = 1'b1;
	 endcase

endmodule

Laboratorios/punto5/sop_pos/punto5_pos_sop_tb.v
`timescale 1ns / 10 ps
module punto5_pos_sop_tb();
//********************************
//declaracion de variables para conexion
 reg inA,inB,inC;
 wire outFsimp,outFpos,outFsop,outFcase;
//********************************
//conexion del circuito
punto5_pos_sop EJR(
.A(inA),
.B(inB),
.C(inC),
.Fsimp(outFsimp),
.Fpos(outFpos),
.Fsop(outFsop),
.Fcase(outFcase)
);
//*********************************
//estimulos
initial begin
  inA=1'b0; inB=1'b0; inC=1'b0;  #20;
  inA=1'b0; inB=1'b0; inC=1'b1;  #20;
  inA=1'b0; inB=1'b1; inC=1'b0;  #20;
  inA=1'b0; inB=1'b1; inC=1'b1;  #20;
  inA=1'b1; inB=1'b0; inC=1'b0;  #20;
  inA=1'b1; inB=1'b0; inC=1'b1;  #20;
  inA=1'b1; inB=1'b1; inC=1'b0;  #20;
  inA=1'b1; inB=1'b1; inC=1'b1;  #20;
  $finish;
end
//************************************
//mostrar resultados con gtkwave
initial begin
  $dumpfile("ARCHIVO.vcd");
  $dumpvars;
end
//**********************************
//mostrar resultados en consola
initial begin
$display("-------|-------|------|------|-------|");
$display(" A B C | Fsimp | Fpos | Fsop | Fcase |");
$display("-------|-------|------|------|-------|");
$monitor(" %b %b %b |   %b   |   %b  |   %b  |   %b   |",inA,inB,inC,outFsimp,outFpos,outFsop,outFcase);
end

endmodule

Laboratorios/punto5/sop_pos/sop_pos/ARCHIVO.vcd
$date
	Sun Nov 22 17:07:49 2020
$end
$version
	Icarus Verilog
$end
$timescale
	10ps
$end
$scope module punto5_pos_sop_tb $end
$var wire 1 ! outFsop $end
$var wire 1 " outFsimp $end
$var wire 1 # outFpos $end
$var wire 1 $ outFcase $end
$var reg 1 % inA $end
$var reg 1 & inB $end
$var reg 1 ' inC $end
$scope module EJR $end
$var wire 1 % A $end
$var wire 1 & B $end
$var wire 1 ' C $end
$var wire 1 # Fpos $end
$var wire 1 " Fsimp $end
$var wire 1 ! Fsop $end
$var reg 1 $ Fcase $end
$upscope $end
$upscope $end
$enddefinitions $end
#0
$dumpvars
0'
0&
0%
0$
0#
0"
0!
$end
#2000
1#
1!
1"
1$
1'
#4000
0#
0!
0"
0$
0'
1&
#6000
1'
#8000
1!
1"
1#
1$
0'
0&
1%
#10000
1'
#12000
0#
0"
0!
0$
0'
1&
#14000
1"
1#
1!
1$
1'
