Laboratorios/cronometro/cronometro.v
module cronometro(
//entradas 
input clk,
input reset, 

//salidas
output reg [3:0]q0,          ///9999
output reg [3:0]q1,
output reg [3:0]q2,
output reg [3:0]q3,//mayor peso
output [15:0]q
);

//circuito
always @ (posedge clk)
	if (reset) begin
	q0<=4'd0;
	q1<=4'd0;
	q2<=4'd0;
	q3<=4'd0;
	end else begin
	if(q0!=4'd9)begin 
	q0<=q0+1;
	end else if(q0==4'd9&&q1!=4'd9) begin
	q0<=4'd0;
	q1<=q1+1;
	end else if(q1==4'd9&&q2!=4'd9)begin 
	q0<=4'd0;
	q1<=4'd0;
	q2<=q2+1;
	end else if(q2==4'd9&&q3!=4'd9)begin 
	q0<=4'd0;
	q1<=4'd0;
	q2<=4'd0;
	q3<=q3+1;
	end
	
	end
	assign q={q3,q2,q1,q0};	


endmodule

Laboratorios/cronometro/cronometro_tb.v
`timescale 1ns / 1ps
module cronometro_tb();

// VARIABLES QUE SE MODIFICAN DENTRO DEL "ALWAYS" 
reg clk;
reg reset;

//OTRAS VARIABLES
wire [3:0]q0;
wire [3:0]q1;
wire [3:0]q2;
wire [3:0]q3;
wire [15:0]q;

//conexion con el circuito que se quiere simular
cronometro U0(
 .clk(clk),   
 .reset(reset),
 .q0(q0),
 .q1(q1),
 .q2(q2),
 .q3(q3),
 .q(q)
);

//estimulos
initial begin
	clk = 1'b1;
	reset = 1'b0;


end

always 
#1 clk = !clk;

initial begin
	 $dumpfile("resultados.vcd"); // guardar resultados de simulación en archivo
	 $dumpvars;
	 
	 reset = 1'b1;

	 #2;
	 
	 reset = 1'b0;
	
	 #22000;
	
$finish;
end

endmodule

Laboratorios/cronometro/resultados.vcd
$date
	Tue Sep 15 10:59:33 2020
$end
$version
	Icarus Verilog
$end
$timescale
	1ps
$end
$scope module cronometro_tb $end
$var wire 4 ! q3 [3:0] $end
$var wire 4 " q2 [3:0] $end
$var wire 4 # q1 [3:0] $end
$var wire 4 $ q0 [3:0] $end
$var wire 16 % q [15:0] $end
$var reg 1 & clk $end
$var reg 1 ' reset $end
$scope module U0 $end
$var wire 1 & clk $end
$var wire 1 ' reset $end
$var wire 16 ( q [15:0] $end
$var reg 4 ) q0 [3:0] $end
$var reg 4 * q1 [3:0] $end
$var reg 4 + q2 [3:0] $end
$var reg 4 , q3 [3:0] $end
$upscope $end
$upscope $end
$enddefinitions $end
#0
$dumpvars
b0 ,
b0 +
b0 *
b0 )
b0 (
1'
1&
b0 %
b0 $
b0 #
b0 "
b0 !
$end
#1000
0&
#2000
b1 %
b1 (
b1 $
b1 )
1&
0'
#3000
0&
#4000
b10 %
b10 (
b10 $
b10 )
1&
#5000
0&
#6000
b11 %
b11 (
b11 $
b11 )
1&
#7000
0&
#8000
b100 %
b100 (
b100 $
b100 )
1&
#9000
0&
#10000
b101 %
b101 (
b101 $
b101 )
1&
#11000
0&
#12000
b110 %
b110 (
b110 $
b110 )
1&
#13000
0&
#14000
b111 %
b111 (
b111 $
b111 )
1&
#15000
0&
#16000
b1000 %
b1000 (
b1000 $
b1000 )
1&
#17000
0&
#18000
b1001 %
b1001 (
b1001 $
b1001 )
1&
#19000
0&
#20000
b1 #
b1 *
b10000 %
b10000 (
b0 $
b0 )
1&
#21000
0&
#22000
b10001 %
b10001 (
b1 $
b1 )
1&
#23000
0&
#24000
b10010 %
b10010 (
b10 $
b10 )
1&
#25000
0&
#26000
b10011 %
b10011 (
b11 $
b11 )
1&
#27000
0&
#28000
b10100 %
b10100 (
b100 $
b100 )
1&
#29000
0&
#30000
b10101 %
b10101 (
b101 $
b101 )
1&
#31000
0&
#32000
b10110 %
b10110 (
b110 $
b110 )
1&
#33000
0&
#34000
b10111 %
b10111 (
b111 $
b111 )
1&
#35000
0&
#36000
b11000 %
b11000 (
b1000 $
b1000 )
1&
#37000
0&
#38000
b11001 %
b11001 (
b1001 $
b1001 )
1&
#39000
0&
#40000
b10 #
b10 *
b100000 %
b100000 (
b0 $
b0 )
1&
#41000
0&
#42000
b100001 %
b100001 (
b1 $
b1 )
1&
#43000
0&
#44000
b100010 %
b100010 (
b10 $
b10 )
1&
#45000
0&
#46000
b100011 %
b100011 (
b11 $
b11 )
1&
#47000
0&
#48000
b100100 %
b100100 (
b100 $
b100 )
1&
#49000
0&
#50000
b100101 %
b100101 (
b101 $
b101 )
1&
#51000
0&
#52000
b100110 %
b100110 (
b110 $
b110 )
1&
#53000
0&
#54000
b100111 %
b100111 (
b111 $
b111 )
1&
#55000
0&
#56000
b101000 %
b101000 (
b1000 $
b1000 )
1&
#57000
0&
#58000
b101001 %
b101001 (
b1001 $
b1001 )
1&
#59000
0&
#60000
b11 #
b11 *
b110000 %
b110000 (
b0 $
b0 )
1&
#61000
0&
#62000
b110001 %
b110001 (
b1 $
b1 )
1&
#63000
0&
#64000
b110010 %
b110010 (
b10 $
b10 )
1&
#65000
0&
#66000
b110011 %
b110011 (
b11 $
b11 )
1&
#67000
0&
#68000
b110100 %
b110100 (
b100 $
b100 )
1&
#69000
0&
#70000
b110101 %
b110101 (
b101 $
b101 )
1&
#71000
0&
#72000
b110110 %
b110110 (
b110 $
b110 )
1&
#73000
0&
#74000
b110111 %
b110111 (
b111 $
b111 )
1&
#75000
0&
#76000
b111000 %
b111000 (
b1000 $
b1000 )
1&
#77000
0&
#78000
b111001 %
b111001 (
b1001 $
b1001 )
1&
#79000
0&
#80000
b100 #
b100 *
b1000000 %
b1000000 (
b0 $
b0 )
1&
#81000
0&
#82000
b1000001 %
b1000001 (
b1 $
b1 )
1&
#83000
0&
#84000
b1000010 %
b1000010 (
b10 $
b10 )
1&
#85000
0&
#86000
b1000011 %
b1000011 (
b11 $
b11 )
1&
#87000
0&
#88000
b1000100 %
b1000100 (
b100 $
b100 )
1&
#89000
0&
#90000
b1000101 %
b1000101 (
b101 $
b101 )
1&
#91000
0&
#92000
b1000110 %
b1000110 (
b110 $
b110 )
1&
#93000
0&
#94000
b1000111 %
b1000111 (
b111 $
b111 )
1&
#95000
0&
#96000
b1001000 %
b1001000 (
b1000 $
b1000 )
1&
#97000
0&
#98000
b1001001 %
b1001001 (
b1001 $
b1001 )
1&
#99000
0&
#100000
b101 #
b101 *
b1010000 %
b1010000 (
b0 $
b0 )
1&
#101000
0&
#102000
b1010001 %
b1010001 (
b1 $
b1 )
1&
#103000
0&
#104000
b1010010 %
b1010010 (
b10 $
b10 )
1&
#105000
0&
#106000
b1010011 %
b1010011 (
b11 $
b11 )
1&
#107000
0&
#108000
b1010100 %
b1010100 (
b100 $
b100 )
1&
#109000
0&
#110000
b1010101 %
b1010101 (
b101 $
b101 )
1&
#111000
0&
#112000
b1010110 %
b1010110 (
b110 $
b110 )
1&
#113000
0&
#114000
b1010111 %
b1010111 (
b111 $
b111 )
1&
#115000
0&
#116000
b1011000 %
b1011000 (
b1000 $
b1000 )
1&
#117000
0&
#118000
b1011001 %
b1011001 (
b1001 $
b1001 )
1&
#119000
0&
#120000
b110 #
b110 *
b1100000 %
b1100000 (
b0 $
b0 )
1&
#121000
0&
#122000
b1100001 %
b1100001 (
b1 $
b1 )
1&
#123000
0&
#124000
b1100010 %
b1100010 (
b10 $
b10 )
1&
#125000
0&
#126000
b1100011 %
b1100011 (
b11 $
b11 )
1&
#127000
0&
#128000
b1100100 %
b1100100 (
b100 $
b100 )
1&
#129000
0&
#130000
b1100101 %
b1100101 (
b101 $
b101 )
1&
#131000
0&
#132000
b1100110 %
b1100110 (
b110 $
b110 )
1&
#133000
0&
#134000
b1100111 %
b1100111 (
b111 $
b111 )
1&
#135000
0&
#136000
b1101000 %
b1101000 (
b1000 $
b1000 )
1&
#137000
0&
#138000
b1101001 %
b1101001 (
b1001 $
b1001 )
1&
#139000
0&
#140000
b111 #
b111 *
b1110000 %
b1110000 (
b0 $
b0 )
1&
#141000
0&
#142000
b1110001 %
b1110001 (
b1 $
b1 )
1&
#143000
0&
#144000
b1110010 %
b1110010 (
b10 $
b10 )
1&
#145000
0&
#146000
b1110011 %
b1110011 (
b11 $
b11 )
1&
#147000
0&
#148000
b1110100 %
b1110100 (
b100 $
b100 )
1&
#149000
0&
#150000
b1110101 %
b1110101 (
b101 $
b101 )
1&
#151000
0&
#152000
b1110110 %
b1110110 (
b110 $
b110 )
1&
#153000
0&
#154000
b1110111 %
b1110111 (
b111 $
b111 )
1&
#155000
0&
#156000
b1111000 %
b1111000 (
b1000 $
b1000 )
1&
#157000
0&
#158000
b1111001 %
b1111001 (
b1001 $
b1001 )
1&
#159000
0&
#160000
b1000 #
b1000 *
b10000000 %
b10000000 (
b0 $
b0 )
1&
#161000
0&
#162000
b10000001 %
b10000001 (
b1 $
b1 )
1&
#163000
0&
#164000
b10000010 %
b10000010 (
b10 $
b10 )
1&
#165000
0&
#166000
b10000011 %
b10000011 (
b11 $
b11 )
1&
#167000
0&
#168000
b10000100 %
b10000100 (
b100 $
b100 )
1&
#169000
0&
#170000
b10000101 %
b10000101 (
b101 $
b101 )
1&
#171000
0&
#172000
b10000110 %
b10000110 (
b110 $
b110 )
1&
#173000
0&
#174000
b10000111 %
b10000111 (
b111 $
b111 )
1&
#175000
0&
#176000
b10001000 %
b10001000 (
b1000 $
b1000 )
1&
#177000
0&
#178000
b10001001 %
b10001001 (
b1001 $
b1001 )
1&
#179000
0&
#180000
b1001 #
b1001 *
b10010000 %
b10010000 (
b0 $
b0 )
1&
#181000
0&
#182000
b10010001 %
b10010001 (
b1 $
b1 )
1&
#183000
0&
#184000
b10010010 %
b10010010 (
b10 $
b10 )
1&
#185000
0&
#186000
b10010011 %
b10010011 (
b11 $
b11 )
1&
#187000
0&
#188000
b10010100 %
b10010100 (
b100 $
b100 )
1&
#189000
0&
#190000
b10010101 %
b10010101 (
b101 $
b101 )
1&
#191000
0&
#192000
b10010110 %
b10010110 (
b110 $
b110 )
1&
#193000
0&
#194000
b10010111 %
b10010111 (
b111 $
b111 )
1&
#195000
0&
#196000
b10011000 %
b10011000 (
b1000 $
b1000 )
1&
#197000
0&
#198000
b10011001 %
b10011001 (
b1001 $
b1001 )
1&
#199000
0&
#200000
b1 "
b1 +
b0 #
b0 *
b100000000 %
b100000000 (
b0 $
b0 )
1&
#201000
0&
#202000
b100000001 %
b100000001 (
b1 $
b1 )
1&
#203000
0&
#204000
b100000010 %
b100000010 (
b10 $
b10 )
1&
#205000
0&
#206000
b100000011 %
b100000011 (
b11 $
b11 )
1&
#207000
0&
#208000
b100000100 %
b100000100 (
b100 $
b100 )
1&
#209000
0&
#210000
b100000101 %
b100000101 (
b101 $
b101 )
1&
#211000
0&
#212000
b100000110 %
b100000110 (
b110 $
b110 )
1&
#213000
0&
#214000
b100000111 %
b100000111 (
b111 $
b111 )
1&
#215000
0&
#216000
b100001000 %
b100001000 (
b1000 $
b1000 )
1&
#217000
0&
#218000
b100001001 %
b100001001 (
b1001 $
b1001 )
1&
#219000
0&
#220000
b1 #
b1 *
b100010000 %
b100010000 (
b0 $
b0 )
1&
#221000
0&
#222000
b100010001 %
b100010001 (
b1 $
b1 )
1&
#223000
0&
#224000
b100010010 %
b100010010 (
b10 $
b10 )
1&
#225000
0&
#226000
b100010011 %
b100010011 (
b11 $
b11 )
1&
#227000
0&
#228000
b100010100 %
b100010100 (
b100 $
b100 )
1&
#229000
0&
#230000
b100010101 %
b100010101 (
b101 $
b101 )
1&
#231000
0&
#232000
b100010110 %
b100010110 (
b110 $
b110 )
1&
#233000
0&
#234000
b100010111 %
b100010111 (
b111 $
b111 )
1&
#235000
0&
#236000
b100011000 %
b100011000 (
b1000 $
b1000 )
1&
#237000
0&
#238000
b100011001 %
b100011001 (
b1001 $
b1001 )
1&
#239000
0&
#240000
b10 #
b10 *
b100100000 %
b100100000 (
b0 $
b0 )
1&
#241000
0&
#242000
b100100001 %
b100100001 (
b1 $
b1 )
1&
#243000
0&
#244000
b100100010 %
b100100010 (
b10 $
b10 )
1&
#245000
0&
#246000
b100100011 %
b100100011 (
b11 $
b11 )
1&
#247000
0&
#248000
b100100100 %
b100100100 (
b100 $
b100 )
1&
#249000
0&
#250000
b100100101 %
b100100101 (
b101 $
b101 )
1&
#251000
0&
#252000
b100100110 %
b100100110 (
b110 $
b110 )
1&
#253000
0&
#254000
b100100111 %
b100100111 (
b111 $
b111 )
1&
#255000
0&
#256000
b100101000 %
b100101000 (
b1000 $
b1000 )
1&
#257000
0&
#258000
b100101001 %
b100101001 (
b1001 $
b1001 )
1&
#259000
0&
#260000
b11 #
b11 *
b100110000 %
b100110000 (
b0 $
b0 )
1&
#261000
0&
#262000
b100110001 %
b100110001 (
b1 $
b1 )
1&
#263000
0&
#264000
b100110010 %
b100110010 (
b10 $
b10 )
1&
#265000
0&
#266000
b100110011 %
b100110011 (
b11 $
b11 )
1&
#267000
0&
#268000
b100110100 %
b100110100 (
b100 $
b100 )
1&
#269000
0&
#270000
b100110101 %
b100110101 (
b101 $
b101 )
1&
#271000
0&
#272000
b100110110 %
b100110110 (
b110 $
b110 )
1&
#273000
0&
#274000
b100110111 %
b100110111 (
b111 $
b111 )
1&
#275000
0&
#276000
b100111000 %
b100111000 (
b1000 $
b1000 )
1&
#277000
0&
#278000
b100111001 %
b100111001 (
b1001 $
b1001 )
1&
#279000
0&
#280000
b100 #
b100 *
b101000000 %
b101000000 (
b0 $
b0 )
1&
#281000
0&
#282000
b101000001 %
b101000001 (
b1 $
b1 )
1&
#283000
0&
#284000
b101000010 %
b101000010 (
b10 $
b10 )
1&
#285000
0&
#286000
b101000011 %
b101000011 (
b11 $
b11 )
1&
#287000
0&
#288000
b101000100 %
b101000100 (
b100 $
b100 )
1&
#289000
0&
#290000
b101000101 %
b101000101 (
b101 $
b101 )
1&
#291000
0&
#292000
b101000110 %
b101000110 (
b110 $
b110 )
1&
#293000
0&
#294000
b101000111 %
b101000111 (
b111 $
b111 )
1&
#295000
0&
#296000
b101001000 %
b101001000 (
b1000 $
b1000 )
1&
#297000
0&
#298000
b101001001 %
b101001001 (
b1001 $
b1001 )
1&
#299000
0&
#300000
b101 #
b101 *
b101010000 %
b101010000 (
b0 $
b0 )
1&
#301000
0&
#302000
b101010001 %
b101010001 (
b1 $
b1 )
1&
#303000
0&
#304000
b101010010 %
b101010010 (
b10 $
b10 )
1&
#305000
0&
#306000
b101010011 %
b101010011 (
b11 $
b11 )
1&
#307000
0&
#308000
b101010100 %
b101010100 (
b100 $
b100 )
1&
#309000
0&
#310000
b101010101 %
b101010101 (
b101 $
b101 )
1&
#311000
0&
#312000
b101010110 %
b101010110 (
b110 $
b110 )
1&
#313000
0&
#314000
b101010111 %
b101010111 (
b111 $
b111 )
1&
#315000
0&
#316000
b101011000 %
b101011000 (
b1000 $
b1000 )
1&
#317000
0&
#318000
b101011001 %
b101011001 (
b1001 $
b1001 )
1&
#319000
0&
#320000
b110 #
b110 *
b101100000 %
b101100000 (
b0 $
b0 )
1&
#321000
0&
#322000
b101100001 %
b101100001 (
b1 $
b1 )
1&
#323000
0&
#324000
b101100010 %
b101100010 (
b10 $
b10 )
1&
#325000
0&
#326000
b101100011 %
b101100011 (
b11 $
b11 )
1&
#327000
0&
#328000
b101100100 %
b101100100 (
b100 $
b100 )
1&
#329000
0&
#330000
b101100101 %
b101100101 (
b101 $
b101 )
1&
#331000
0&
#332000
b101100110 %
b101100110 (
b110 $
b110 )
1&
#333000
0&
#334000
b101100111 %
b101100111 (
b111 $
b111 )
1&
#335000
0&
#336000
b101101000 %
b101101000 (
b1000 $
b1000 )
1&
#337000
0&
#338000
b101101001 %
b101101001 (
b1001 $
b1001 )
1&
#339000
0&
#340000
b111 #
b111 *
b101110000 %
b101110000 (
b0 $
b0 )
1&
#341000
0&
#342000
b101110001 %
b101110001 (
b1 $
b1 )
1&
#343000
0&
#344000
b101110010 %
b101110010 (
b10 $
b10 )
1&
#345000
0&
#346000
b101110011 %
b101110011 (
b11 $
b11 )
1&
#347000
0&
#348000
b101110100 %
b101110100 (
b100 $
b100 )
1&
#349000
0&
#350000
b101110101 %
b101110101 (
b101 $
b101 )
1&
#351000
0&
#352000
b101110110 %
b101110110 (
b110 $
b110 )
1&
#353000
0&
#354000
b101110111 %
b101110111 (
b111 $
b111 )
1&
#355000
0&
#356000
b101111000 %
b101111000 (
b1000 $
b1000 )
1&
#357000
0&
#358000
b101111001 %
b101111001 (
b1001 $
b1001 )
1&
#359000
0&
#360000
b1000 #
b1000 *
b110000000 %
b110000000 (
b0 $
b0 )
1&
#361000
0&
#362000
b110000001 %
b110000001 (
b1 $
b1 )
1&
#363000
0&
#364000
b110000010 %
b110000010 (
b10 $
b10 )
1&
#365000
0&
#366000
b110000011 %
b110000011 (
b11 $
b11 )
1&
#367000
0&
#368000
b110000100 %
b110000100 (
b100 $
b100 )
1&
#369000
0&
#370000
b110000101 %
b110000101 (
b101 $
b101 )
1&
#371000
0&
#372000
b110000110 %
b110000110 (
b110 $
b110 )
1&
#373000
0&
#374000
b110000111 %
b110000111 (
b111 $
b111 )
1&
#375000
0&
#376000
b110001000 %
b110001000 (
b1000 $
b1000 )
1&
#377000
0&
#378000
b110001001 %
b110001001 (
b1001 $
b1001 )
1&
#379000
0&
#380000
b1001 #
b1001 *
b110010000 %
b110010000 (
b0 $
b0 )
1&
#381000
0&
#382000
b110010001 %
b110010001 (
b1 $
b1 )
1&
#383000
0&
#384000
b110010010 %
b110010010 (
b10 $
b10 )
1&
#385000
0&
#386000
b110010011 %
b110010011 (
b11 $
b11 )
1&
#387000
0&
#388000
b110010100 %
b110010100 (
b100 $
b100 )
1&
#389000
0&
#390000
b110010101 %
b110010101 (
b101 $
b101 )
1&
#391000
0&
#392000
b110010110 %
b110010110 (
b110 $
b110 )
1&
#393000
0&
#394000
b110010111 %
b110010111 (
b111 $
b111 )
1&
#395000
0&
#396000
b110011000 %
b110011000 (
b1000 $
b1000 )
1&
#397000
0&
#398000
b110011001 %
b110011001 (
b1001 $
b1001 )
1&
#399000
0&
#400000
b10 "
b10 +
b0 #
b0 *
b1000000000 %
b1000000000 (
b0 $
b0 )
1&
#401000
0&
#402000
b1000000001 %
b1000000001 (
b1 $
b1 )
1&
#403000
0&
#404000
b1000000010 %
b1000000010 (
b10 $
b10 )
1&
#405000
0&
#406000
b1000000011 %
b1000000011 (
b11 $
b11 )
1&
#407000
0&
#408000
b1000000100 %
b1000000100 (
b100 $
b100 )
1&
#409000
0&
#410000
b1000000101 %
b1000000101 (
b101 $
b101 )
1&
#411000
0&
#412000
b1000000110 %
b1000000110 (
b110 $
b110 )
1&
#413000
0&
#414000
b1000000111 %
b1000000111 (
b111 $
b111 )
1&
#415000
0&
#416000
b1000001000 %
b1000001000 (
b1000 $
b1000 )
1&
#417000
0&
#418000
b1000001001 %
b1000001001 (
b1001 $
b1001 )
1&
#419000
0&
#420000
b1 #
b1 *
b1000010000 %
b1000010000 (
b0 $
b0 )
1&
#421000
0&
#422000
b1000010001 %
b1000010001 (
b1 $
b1 )
1&
#423000
0&
#424000
b1000010010 %
b1000010010 (
b10 $
b10 )
1&
#425000
0&
#426000
b1000010011 %
b1000010011 (
b11 $
b11 )
1&
#427000
0&
#428000
b1000010100 %
b1000010100 (
b100 $
b100 )
1&
#429000
0&
#430000
b1000010101 %
b1000010101 (
b101 $
b101 )
1&
#431000
0&
#432000
b1000010110 %
b1000010110 (
b110 $
b110 )
1&
#433000
0&
#434000
b1000010111 %
b1000010111 (
b111 $
b111 )
1&
#435000
0&
#436000
b1000011000 %
b1000011000 (
b1000 $
b1000 )
1&
#437000
0&
#438000
b1000011001 %
b1000011001 (
b1001 $
b1001 )
1&
#439000
0&
#440000
b10 #
b10 *
b1000100000 %
b1000100000 (
b0 $
b0 )
1&
#441000
0&
#442000
b1000100001 %
b1000100001 (
b1 $
b1 )
1&
#443000
0&
#444000
b1000100010 %
b1000100010 (
b10 $
b10 )
1&
#445000
0&
#446000
b1000100011 %
b1000100011 (
b11 $
b11 )
1&
#447000
0&
#448000
b1000100100 %
b1000100100 (
b100 $
b100 )
1&
#449000
0&
#450000
b1000100101 %
b1000100101 (
b101 $
b101 )
1&
#451000
0&
#452000
b1000100110 %
b1000100110 (
b110 $
b110 )
1&
#453000
0&
#454000
b1000100111 %
b1000100111 (
b111 $
b111 )
1&
#455000
0&
#456000
b1000101000 %
b1000101000 (
b1000 $
b1000 )
1&
#457000
0&
#458000
b1000101001 %
b1000101001 (
b1001 $
b1001 )
1&
#459000
0&
#460000
b11 #
b11 *
b1000110000 %
b1000110000 (
b0 $
b0 )
1&
#461000
0&
#462000
b1000110001 %
b1000110001 (
b1 $
b1 )
1&
#463000
0&
#464000
b1000110010 %
b1000110010 (
b10 $
b10 )
1&
#465000
0&
#466000
b1000110011 %
b1000110011 (
b11 $
b11 )
1&
#467000
0&
#468000
b1000110100 %
b1000110100 (
b100 $
b100 )
1&
#469000
0&
#470000
b1000110101 %
b1000110101 (
b101 $
b101 )
1&
#471000
0&
#472000
b1000110110 %
b1000110110 (
b110 $
b110 )
1&
#473000
0&
#474000
b1000110111 %
b1000110111 (
b111 $
b111 )
1&
#475000
0&
#476000
b1000111000 %
b1000111000 (
b1000 $
b1000 )
1&
#477000
0&
#478000
b1000111001 %
b1000111001 (
b1001 $
b1001 )
1&
#479000
0&
#480000
b100 #
b100 *
b1001000000 %
b1001000000 (
b0 $
b0 )
1&
#481000
0&
#482000
b1001000001 %
b1001000001 (
b1 $
b1 )
1&
#483000
0&
#484000
b1001000010 %
b1001000010 (
b10 $
b10 )
1&
#485000
0&
#486000
b1001000011 %
b1001000011 (
b11 $
b11 )
1&
#487000
0&
#488000
b1001000100 %
b1001000100 (
b100 $
b100 )
1&
#489000
0&
#490000
b1001000101 %
b1001000101 (
b101 $
b101 )
1&
#491000
0&
#492000
b1001000110 %
b1001000110 (
b110 $
b110 )
1&
#493000
0&
#494000
b1001000111 %
b1001000111 (
b111 $
b111 )
1&
#495000
0&
#496000
b1001001000 %
b1001001000 (
b1000 $
b1000 )
1&
#497000
0&
#498000
b1001001001 %
b1001001001 (
b1001 $
b1001 )
1&
#499000
0&
#500000
b101 #
b101 *
b1001010000 %
b1001010000 (
b0 $
b0 )
1&
#501000
0&
#502000
b1001010001 %
b1001010001 (
b1 $
b1 )
1&
#503000
0&
#504000
b1001010010 %
b1001010010 (
b10 $
b10 )
1&
#505000
0&
#506000
b1001010011 %
b1001010011 (
b11 $
b11 )
1&
#507000
0&
#508000
b1001010100 %
b1001010100 (
b100 $
b100 )
1&
#509000
0&
#510000
b1001010101 %
b1001010101 (
b101 $
b101 )
1&
#511000
0&
#512000
b1001010110 %
b1001010110 (
b110 $
b110 )
1&
#513000
0&
#514000
b1001010111 %
b1001010111 (
b111 $
b111 )
1&
#515000
0&
#516000
b1001011000 %
b1001011000 (
b1000 $
b1000 )
1&
#517000
0&
#518000
b1001011001 %
b1001011001 (
b1001 $
b1001 )
1&
#519000
0&
#520000
b110 #
b110 *
b1001100000 %
b1001100000 (
b0 $
b0 )
1&
#521000
0&
#522000
b1001100001 %
b1001100001 (
b1 $
b1 )
1&
#523000
0&
#524000
b1001100010 %
b1001100010 (
b10 $
b10 )
1&
#525000
0&
#526000
b1001100011 %
b1001100011 (
b11 $
b11 )
1&
#527000
0&
#528000
b1001100100 %
b1001100100 (
b100 $
b100 )
1&
#529000
0&
#530000
b1001100101 %
b1001100101 (
b101 $
b101 )
1&
#531000
0&
#532000
b1001100110 %
b1001100110 (
b110 $
b110 )
1&
#533000
0&
#534000
b1001100111 %
b1001100111 (
b111 $
b111 )
1&
#535000
0&
#536000
b1001101000 %
b1001101000 (
b1000 $
b1000 )
1&
#537000
0&
#538000
b1001101001 %
b1001101001 (
b1001 $
b1001 )
1&
#539000
0&
#540000
b111 #
b111 *
b1001110000 %
b1001110000 (
b0 $
b0 )
1&
#541000
0&
#542000
b1001110001 %
b1001110001 (
b1 $
b1 )
1&
#543000
0&
#544000
b1001110010 %
b1001110010 (
b10 $
b10 )
1&
#545000
0&
#546000
b1001110011 %
b1001110011 (
b11 $
b11 )
1&
#547000
0&
#548000
b1001110100 %
b1001110100 (
b100 $
b100 )
1&
#549000
0&
#550000
b1001110101 %
b1001110101 (
b101 $
b101 )
1&
#551000
0&
#552000
b1001110110 %
b1001110110 (
b110 $
b110 )
1&
#553000
0&
#554000
b1001110111 %
b1001110111 (
b111 $
b111 )
1&
#555000
0&
#556000
b1001111000 %
b1001111000 (
b1000 $
b1000 )
1&
#557000
0&
#558000
b1001111001 %
b1001111001 (
b1001 $
b1001 )
1&
#559000
0&
#560000
b1000 #
b1000 *
b1010000000 %
b1010000000 (
b0 $
b0 )
1&
#561000
0&
#562000
b1010000001 %
b1010000001 (
b1 $
b1 )
1&
#563000
0&
#564000
b1010000010 %
b1010000010 (
b10 $
b10 )
1&
#565000
0&
#566000
b1010000011 %
b1010000011 (
b11 $
b11 )
1&
#567000
0&
#568000
b1010000100 %
b1010000100 (
b100 $
b100 )
1&
#569000
0&
#570000
b1010000101 %
b1010000101 (
b101 $
b101 )
1&
#571000
0&
#572000
b1010000110 %
b1010000110 (
b110 $
b110 )
1&
#573000
0&
#574000
b1010000111 %
b1010000111 (
b111 $
b111 )
1&
#575000
0&
#576000
b1010001000 %
b1010001000 (
b1000 $
b1000 )
1&
#577000
0&
#578000
b1010001001 %
b1010001001 (
b1001 $
b1001 )
1&
#579000
0&
#580000
b1001 #
b1001 *
b1010010000 %
b1010010000 (
b0 $
b0 )
1&
#581000
0&
#582000
b1010010001 %
b1010010001 (
b1 $
b1 )
1&
#583000
0&
#584000
b1010010010 %
b1010010010 (
b10 $
b10 )
1&
#585000
0&
#586000
b1010010011 %
b1010010011 (
b11 $
b11 )
1&
#587000
0&
#588000
b1010010100 %
b1010010100 (
b100 $
b100 )
1&
#589000
0&
#590000
b1010010101 %
b1010010101 (
b101 $
b101 )
1&
#591000
0&
#592000
b1010010110 %
b1010010110 (
b110 $
b110 )
1&
#593000
0&
#594000
b1010010111 %
b1010010111 (
b111 $
b111 )
1&
#595000
0&
#596000
b1010011000 %
b1010011000 (
b1000 $
b1000 )
1&
#597000
0&
#598000
b1010011001 %
b1010011001 (
b1001 $
b1001 )
1&
#599000
0&
#600000
b11 "
b11 +
b0 #
b0 *
b1100000000 %
b1100000000 (
b0 $
b0 )
1&
#601000
0&
#602000
b1100000001 %
b1100000001 (
b1 $
b1 )
1&
#603000
0&
#604000
b1100000010 %
b1100000010 (
b10 $
b10 )
1&
#605000
0&
#606000
b1100000011 %
b1100000011 (
b11 $
b11 )
1&
#607000
0&
#608000
b1100000100 %
b1100000100 (
b100 $
b100 )
1&
#609000
0&
#610000
b1100000101 %
b1100000101 (
b101 $
b101 )
1&
#611000
0&
#612000
b1100000110 %
b1100000110 (
b110 $
b110 )
1&
#613000
0&
#614000
b1100000111 %
b1100000111 (
b111 $
b111 )
1&
#615000
0&
#616000
b1100001000 %
b1100001000 (
b1000 $
b1000 )
1&
#617000
0&
#618000
b1100001001 %
b1100001001 (
b1001 $
b1001 )
1&
#619000
0&
#620000
b1 #
b1 *
b1100010000 %
b1100010000 (
b0 $
b0 )
1&
#621000
0&
#622000
b1100010001 %
b1100010001 (
b1 $
b1 )
1&
#623000
0&
#624000
b1100010010 %
b1100010010 (
b10 $
b10 )
1&
#625000
0&
#626000
b1100010011 %
b1100010011 (
b11 $
b11 )
1&
#627000
0&
#628000
b1100010100 %
b1100010100 (
b100 $
b100 )
1&
#629000
0&
#630000
b1100010101 %
b1100010101 (
b101 $
b101 )
1&
#631000
0&
#632000
b1100010110 %
b1100010110 (
b110 $
b110 )
1&
#633000
0&
#634000
b1100010111 %
b1100010111 (
b111 $
b111 )
1&
#635000
0&
#636000
b1100011000 %
b1100011000 (
b1000 $
b1000 )
1&
#637000
0&
#638000
b1100011001 %
b1100011001 (
b1001 $
b1001 )
1&
#639000
0&
#640000
b10 #
b10 *
b1100100000 %
b1100100000 (
b0 $
b0 )
1&
#641000
0&
#642000
b1100100001 %
b1100100001 (
b1 $
b1 )
1&
#643000
0&
#644000
b1100100010 %
b1100100010 (
b10 $
b10 )
1&
#645000
0&
#646000
b1100100011 %
b1100100011 (
b11 $
b11 )
1&
#647000
0&
#648000
b1100100100 %
b1100100100 (
b100 $
b100 )
1&
#649000
0&
#650000
b1100100101 %
b1100100101 (
b101 $
b101 )
1&
#651000
0&
#652000
b1100100110 %
b1100100110 (
b110 $
b110 )
1&
#653000
0&
#654000
b1100100111 %
b1100100111 (
b111 $
b111 )
1&
#655000
0&
#656000
b1100101000 %
b1100101000 (
b1000 $
b1000 )
1&
#657000
0&
#658000
b1100101001 %
b1100101001 (
b1001 $
b1001 )
1&
#659000
0&
#660000
b11 #
b11 *
b1100110000 %
b1100110000 (
b0 $
b0 )
1&
#661000
0&
#662000
b1100110001 %
b1100110001 (
b1 $
b1 )
1&
#663000
0&
#664000
b1100110010 %
b1100110010 (
b10 $
b10 )
1&
#665000
0&
#666000
b1100110011 %
b1100110011 (
b11 $
b11 )
1&
#667000
0&
#668000
b1100110100 %
b1100110100 (
b100 $
b100 )
1&
#669000
0&
#670000
b1100110101 %
b1100110101 (
b101 $
b101 )
1&
#671000
0&
#672000
b1100110110 %
b1100110110 (
b110 $
b110 )
1&
#673000
0&
#674000
b1100110111 %
b1100110111 (
b111 $
b111 )
1&
#675000
0&
#676000
b1100111000 %
b1100111000 (
b1000 $
b1000 )
1&
#677000
0&
#678000
b1100111001 %
b1100111001 (
b1001 $
b1001 )
1&
#679000
0&
#680000
b100 #
b100 *
b1101000000 %
b1101000000 (
b0 $
b0 )
1&
#681000
0&
#682000
b1101000001 %
b1101000001 (
b1 $
b1 )
1&
#683000
0&
#684000
b1101000010 %
b1101000010 (
b10 $
b10 )
1&
#685000
0&
