Codigos/mux/2a1/mux2a1.v
// mux 2 a 1 
module mux2a1(
input [2:0] A,
input [2:0] B,
input s0,
output [2:0] F
);

assign F=s0?A:B;

endmodule

Codigos/mux/2a1/estimulos_mux2a1.v
`timescale 1ns / 10 ps
module estimulos_mux2a1 ();
//********************************
//declaracion de variables para conexion
 reg [2:0]A;
 reg [2:0]B;
 reg s0;
 wire  [2:0]F;
//********************************
//conexion del circuito
mux2a1 S1(
.A(A),
.B(B),
.s0(s0),
.F(F)
);
//*********************************
//estimulos
initial begin
   A=3'b000; B=3'b001;  s0=1'b0; #20;
   A=3'b001; B=3'b000;  s0=1'b1; #20;
   A=3'b010; B=3'b011;  s0=1'b0; #20;
   A=3'b011; B=3'b010;  s0=1'b1; #20;
   A=3'b100; B=3'b100;  s0=1'b0; #20;
   A=3'b101; B=3'b101;  s0=1'b1; #20;
   A=3'b100; B=3'b101;  s0=1'b1; #20;
   A=3'b011; B=3'b000;  s0=1'b0; #20;
  $finish;
end
//************************************
//mostrar resultados con gtkwave
initial begin
  $dumpfile("ARCHIVO.vcd");
  $dumpvars;
end
//**********************************
//mostrar resultados en consola
initial begin
$display("-----------|-----|");
$display("  A   B  s0|  F  |");
$display("-----------|-----|");
$monitor(" %b %b %b | %b |",A,B,s0,F);
end

endmodule

Codigos/mux/2a1/ARCHIVO.vcd
$date
	Sun Jan 17 16:26:36 2021
$end
$version
	Icarus Verilog
$end
$timescale
	10ps
$end
$scope module estimulos_mux2a1 $end
$var wire 3 ! F [2:0] $end
$var reg 3 " A [2:0] $end
$var reg 3 # B [2:0] $end
$var reg 1 $ s0 $end
$scope module S1 $end
$var wire 3 % A [2:0] $end
$var wire 3 & B [2:0] $end
$var wire 1 $ s0 $end
$var wire 3 ' F [2:0] $end
$upscope $end
$upscope $end
$enddefinitions $end
#0
$dumpvars
b1 '
b1 &
b0 %
0$
b1 #
b0 "
b1 !
$end
#2000
1$
b0 #
b0 &
b1 "
b1 %
#4000
b11 !
b11 '
0$
b11 #
b11 &
b10 "
b10 %
#6000
1$
b10 #
b10 &
b11 "
b11 %
#8000
b100 !
b100 '
0$
b100 #
b100 &
b100 "
b100 %
#10000
b101 !
b101 '
1$
b101 #
b101 &
b101 "
b101 %
#12000
b100 !
b100 '
b100 "
b100 %
#14000
b0 !
b0 '
0$
b0 #
b0 &
b11 "
b11 %
