Laboratorios/lab6/labsland/display2.v
module display2(
//entradas y salidas
//modo tipo ancho nombre
 input A,B,C,D,
 output a,b,c,d,e,f,g
);
assign a=(~A&~B&~C&D)|(~A&B&~C&~D)|(~A&B&C&~D)|(A&~B&C&~D)|(A&~B&C&D)|(A&B&~C&~D)|(A&B&C&~D)|(A&B&C&D);
assign b=(~A&B&~C&D)|(~A&B&C&~D)|(A&~B&C&~D)|(A&B&~C&D)|(A&~B&C&D)|(A&B&C&D)|(A&B&C&~D);
assign c=(~A&~B&C&~D)|(A&~B&C&~D)|(A&B&~C&~D)|(A&B&~C&D)|(A&B&C&~D)|(A&B&C&D);
assign d=(~A&~B&~C&D)|(~A&B&~C&~D)|(~A&B&C&D)|(A&~B&~C&D)|(A&B&~C&~D)|(A&B&C&D);
assign e=(A|B|C|D)&(A|B|~C|D)&(A|~B|~C|D)&(~A|B|C|D)&(~A|B|~C|D)&(~A|~B|~C|D);
assign f=(~A&~B&~C&D)|(~A&~B&C&~D)|(~A&~B&C&D)|(~A&B&C&D)|(A&~B&C&~D)|(A&~B&C&D)|(A&B&C&D);
assign g=(~A&~B&~C&~D)|(~A&~B&~C&D)|(~A&B&C&D)|(A&B&C&D);
endmodule

Laboratorios/lab6/cmd/display_tb.v
`timescale 1ns / 10 ps
module display_tb();
//********************************
//declaracion de variables para conexion
 reg [3:0] in;
 wire a,b,c,d,e,f;
//********************************
//conexion del circuito
display2 EJR(
.A(in[3]),
.B(in[2]),
.C(in[1]),
.D(in[0]),
.a(a),
.b(b),
.c(c),
.d(d),
.e(e),
.f(f),
.g(g)
);
//*********************************
initial begin
   in=0;     #20;
   repeat (15) begin
   in=in+1;  #20;
   end     // espera
  $finish;  // termina la simulación
end
//mostrar resultados con gtkwave
initial begin
  $dumpfile("ARCHIVO.vcd");
  $dumpvars;
end
//**********************************
//mostrar resultados en consola
initial begin
$display("|------|---|---|---|---|---|---|---|");
$display("| ABCD | a | b | c | d | e | f | g |");
$display("|------|---|---|---|---|---|---|---|");
$monitor("| %b | %b | %b | %b | %b | %b | %b | %b |",in,a,b,c,d,e,f,g);
end

endmodule

Laboratorios/lab6/cmd/ARCHIVO.vcd
$date
	Thu Sep 09 06:45:18 2021
$end
$version
	Icarus Verilog
$end
$timescale
	10ps
$end
$scope module display_tb $end
$var wire 1 ! g $end
$var wire 1 " f $end
$var wire 1 # e $end
$var wire 1 $ d $end
$var wire 1 % c $end
$var wire 1 & b $end
$var wire 1 ' a $end
$var reg 4 ( in [3:0] $end
$scope module EJR $end
$var wire 1 ) A $end
$var wire 1 * B $end
$var wire 1 + C $end
$var wire 1 , D $end
$var wire 1 ' a $end
$var wire 1 & b $end
$var wire 1 % c $end
$var wire 1 $ d $end
$var wire 1 # e $end
$var wire 1 " f $end
$var wire 1 ! g $end
$upscope $end
$upscope $end
$enddefinitions $end
#0
$dumpvars
0,
0+
0*
0)
b0 (
0'
0&
0%
0$
0#
0"
1!
$end
#2000
1'
1"
1$
1#
1,
b1 (
#4000
0'
1%
0$
0#
0!
1+
0,
b10 (
#6000
0%
1#
1,
b11 (
#8000
1'
1$
0!
1#
0"
1*
0+
0,
b100 (
#10000
0'
1&
0$
1,
b101 (
#12000
1'
0#
0$
1+
0,
b110 (
#14000
0'
0&
1$
1#
1"
1!
1,
b111 (
#16000
0$
0#
0"
0!
1)
0*
0+
0,
b1000 (
#18000
1$
1#
1,
b1001 (
#20000
1'
1&
1%
1"
0$
0#
1+
0,
b1010 (
#22000
0%
1#
1,
b1011 (
#24000
1%
1$
1'
0&
1#
0"
1*
0+
0,
b1100 (
#26000
0'
1&
0$
1,
b1101 (
#28000
0#
1'
0$
1+
0,
b1110 (
#30000
1$
1#
1"
1!
1,
b1111 (
