Laboratorios/EF3/EF3.v
module EF3
(   // ENTRADAS y SALIDAS
    input A,B,C,D,
    output reg [4:0] F
);
// = = = = = = = = = = = = =
// DECLARACIÓN DE VARIABLES
wire [3:0] conca;

// = = = = = = = = = = = = =
// DESCRIPCIÓN DEL CIRCUITO

assign conca ={A,B,C,D};
// -------------------------
 always @(*)
 case (conca)
 4'd0: F= 5'b10100;
 4'd1: F= 5'b10011;
 4'd2: F= 5'b10011;
 4'd3: F= 5'b10010;
 4'd4: F= 5'b10010;
 4'd5: F= 5'b10001;
 4'd6: F= 5'b10001;
 4'd7: F= 5'b10000;
 4'd8: F= 5'b10000;
 4'd9: F= 5'b01111;
 4'd10: F = 5'b01111;
 4'd11: F = 5'b01110;
 4'd12: F = 5'b01110;
 4'd13: F = 5'b01101;
 4'd14: F = 5'b01101;
 4'd15: F = 5'b01100;
 endcase

endmodule

Laboratorios/EF3/EF3_tb.v
module EF3_tb();
// DECLARACIÓN DE CONSTANTES Y VARIABLES `
reg [3:0] in;
wire [4:0] F;

// ===============================================
// CONEXIÓN DEL CIRCUITO QUE SE QUIERE SIMULAR
EF3  OUT(
  .A(in[3]),
  .B(in[2]),
  .C(in[1]),
  .D(in[0]),
  .F(F)
);
// ===============================================
// ESTÍMULOS: situaciones que se quieren observar en la simulación
initial begin
   in=0;     #20;
   repeat (15) begin
   in=in+1;  #20;
   end     // espera
  $finish;  // termina la simulación
end
// ===============================================
initial begin // los resultados se guardan en ARCHIVO.vcd
  $dumpfile("ARCHIVO.vcd");
  $dumpvars;
end
// ===============================================
initial begin
$display("|--------|-------|");
$display("|  ABCD  |   F   |");
$display("|--------|-------|");
$monitor("|  %b  | %b |",in,F);
end
// -----------------------------------------------
endmodule

Laboratorios/EF3/ARCHIVO.vcd
$date
	Sat Sep 04 15:48:16 2021
$end
$version
	Icarus Verilog
$end
$timescale
	1s
$end
$scope module EF3_tb $end
$var wire 5 ! F [4:0] $end
$var reg 4 " in [3:0] $end
$scope module OUT $end
$var wire 1 # A $end
$var wire 1 $ B $end
$var wire 1 % C $end
$var wire 1 & D $end
$var wire 4 ' conca [3:0] $end
$var reg 5 ( F [4:0] $end
$upscope $end
$upscope $end
$enddefinitions $end
#0
$dumpvars
b10100 (
b0 '
0&
0%
0$
0#
b0 "
b10100 !
$end
#20
b10011 !
b10011 (
b1 '
1&
b1 "
#40
1%
b10 '
0&
b10 "
#60
b10010 !
b10010 (
b11 '
1&
b11 "
#80
1$
0%
b100 '
0&
b100 "
#100
b10001 !
b10001 (
b101 '
1&
b101 "
#120
1%
b110 '
0&
b110 "
#140
b10000 !
b10000 (
b111 '
1&
b111 "
#160
1#
0$
0%
b1000 '
0&
b1000 "
#180
b1111 !
b1111 (
b1001 '
1&
b1001 "
#200
1%
b1010 '
0&
b1010 "
#220
b1110 !
b1110 (
b1011 '
1&
b1011 "
#240
1$
0%
b1100 '
0&
b1100 "
#260
b1101 !
b1101 (
b1101 '
1&
b1101 "
#280
1%
b1110 '
0&
b1110 "
#300
b1100 !
b1100 (
b1111 '
1&
b1111 "
