Codigos/comparadores/mayor/mayor.v
//comparador mayor

module mayor(
   input [2:0] A,
   input [2:0] B,
   output F
);

assign F=(A>B);

endmodule

Codigos/comparadores/mayor/estimulos_mayor.v
`timescale 1ns / 10 ps
module estimulos_mayor ();
//********************************
//declaracion de variables para conexion
 reg [2:0]A;
 reg [2:0]B;
 wire F;
//********************************
//conexion del circuito
mayor S1(
.A(A),
.B(B),
.F(F)
);
//*********************************
//estimulos
initial begin
  A=3'b000; B=3'b001;   #20;
  A=3'b001; B=3'b000;   #20;
  A=3'b010; B=3'b011;   #20;
  A=3'b011; B=3'b010;   #20;
  A=3'b100; B=3'b100;   #20;
  A=3'b101; B=3'b101;   #20;
  A=3'b100; B=3'b101;   #20;
  A=3'b011; B=3'b000;   #20;
  $finish;
end
//************************************
//mostrar resultados con gtkwave
initial begin
  $dumpfile("ARCHIVO.vcd");
  $dumpvars;
end
//**********************************
//mostrar resultados en consola
initial begin
$display("---------|---|");
$display("  A   B  | F |");
$display("---------|---|");
$monitor(" %b %b | %b |",A,B,F);
end

endmodule

Codigos/comparadores/mayor/ARCHIVO.vcd
$date
	Sun Jan 17 15:37:45 2021
$end
$version
	Icarus Verilog
$end
$timescale
	10ps
$end
$scope module estimulos_mayor $end
$var wire 1 ! F $end
$var reg 3 " A [2:0] $end
$var reg 3 # B [2:0] $end
$scope module S1 $end
$var wire 3 $ A [2:0] $end
$var wire 3 % B [2:0] $end
$var wire 1 ! F $end
$upscope $end
$upscope $end
$enddefinitions $end
#0
$dumpvars
b1 %
b0 $
b1 #
b0 "
0!
$end
#2000
1!
b0 #
b0 %
b1 "
b1 $
#4000
0!
b11 #
b11 %
b10 "
b10 $
#6000
1!
b10 #
b10 %
b11 "
b11 $
#8000
0!
b100 #
b100 %
b100 "
b100 $
#10000
b101 #
b101 %
0!
b101 "
b101 $
#12000
b100 "
b100 $
#14000
1!
b0 #
b0 %
b11 "
b11 $
