Laboratorios/Temporizador/temporizador.v
module temporizador(
//entradas 
input clk,
input reset, 
input enable, 

//salidas
output reg [3:0]q0,          
output reg [2:0]q1,
output reg q2
);

//circuito
always @ (posedge clk)
	if (reset) begin
	q0<=4'd0;
	q1<=3'd1;
	q2<=1'd1;
	end else if(enable)begin
	if(q0!=4'd0)begin 
	q0<=q0-1;
	end else if(q0==4'd0&&q1!=3'd0) begin
	q0<=4'd9;
	q1<=q1-1;
	end else if(q0==4'd0&&q1==3'd0&&q2!=1'd0)begin 
	q0<=4'd9;
	q1<=3'd5;
	q2<=1'd0;
	end 	
	
	end

endmodule

Laboratorios/Temporizador/temporizador_tb.v
`timescale 1ns / 1ps
module temporizador_tb();

// VARIABLES QUE SE MODIFICAN DENTRO DEL "ALWAYS" 
reg clk;
reg reset;
reg enable;

//OTRAS VARIABLES
wire [3:0]q0;
wire [2:0]q1;


//conexion con el circuito que se quiere simular
temporizador U0(
 .clk(clk),   
 .reset(reset),
 .enable(enable),
 .q0(q0),
 .q1(q1)
);

//estimulos
initial begin
	clk = 1'b1;
	reset = 1'b0;
	enable = 1'b0;
end

always 
#1 clk = !clk;

initial begin
	 $dumpfile("resultados.vcd"); // guardar resultados de simulación en archivo
	 $dumpvars;
	 
	 reset = 1'b1;
	 enable = 1'b1;

	 #2;
	 
	 reset = 1'b0;
	 enable = 1'b1; #10;
	 enable = 1'b0; #10;
	 enable = 1'b1; #150;
	
$finish;
end

endmodule

Laboratorios/Temporizador/resultados.vcd
$date
	Mon Mar 01 10:02:30 2021
$end
$version
	Icarus Verilog
$end
$timescale
	1ps
$end
$scope module temporizador_tb $end
$var wire 3 ! q1 [2:0] $end
$var wire 4 " q0 [3:0] $end
$var reg 1 # clk $end
$var reg 1 $ enable $end
$var reg 1 % reset $end
$scope module U0 $end
$var wire 1 # clk $end
$var wire 1 $ enable $end
$var wire 1 % reset $end
$var reg 4 & q0 [3:0] $end
$var reg 3 ' q1 [2:0] $end
$var reg 1 ( q2 $end
$upscope $end
$upscope $end
$enddefinitions $end
#0
$dumpvars
1(
b1 '
b0 &
1%
1$
1#
b0 "
b1 !
$end
#1000
0#
#2000
b0 !
b0 '
b1001 "
b1001 &
1#
0%
#3000
0#
#4000
b1000 "
b1000 &
1#
#5000
0#
#6000
b111 "
b111 &
1#
#7000
0#
#8000
b110 "
b110 &
1#
#9000
0#
#10000
b101 "
b101 &
1#
#11000
0#
#12000
1#
0$
#13000
0#
#14000
1#
#15000
0#
#16000
1#
#17000
0#
#18000
1#
#19000
0#
#20000
1#
#21000
0#
#22000
b100 "
b100 &
1#
1$
#23000
0#
#24000
b11 "
b11 &
1#
#25000
0#
#26000
b10 "
b10 &
1#
#27000
0#
#28000
b1 "
b1 &
1#
#29000
0#
#30000
b0 "
b0 &
1#
#31000
0#
#32000
0(
b101 !
b101 '
b1001 "
b1001 &
1#
#33000
0#
#34000
b1000 "
b1000 &
1#
#35000
0#
#36000
b111 "
b111 &
1#
#37000
0#
#38000
b110 "
b110 &
1#
#39000
0#
#40000
b101 "
b101 &
1#
#41000
0#
#42000
b100 "
b100 &
1#
#43000
0#
#44000
b11 "
b11 &
1#
#45000
0#
#46000
b10 "
b10 &
1#
#47000
0#
#48000
b1 "
b1 &
1#
#49000
0#
#50000
b0 "
b0 &
1#
#51000
0#
#52000
b100 !
b100 '
b1001 "
b1001 &
1#
#53000
0#
#54000
b1000 "
b1000 &
1#
#55000
0#
#56000
b111 "
b111 &
1#
#57000
0#
#58000
b110 "
b110 &
1#
#59000
0#
#60000
b101 "
b101 &
1#
#61000
0#
#62000
b100 "
b100 &
1#
#63000
0#
#64000
b11 "
b11 &
1#
#65000
0#
#66000
b10 "
b10 &
1#
#67000
0#
#68000
b1 "
b1 &
1#
#69000
0#
#70000
b0 "
b0 &
1#
#71000
0#
#72000
b11 !
b11 '
b1001 "
b1001 &
1#
#73000
0#
#74000
b1000 "
b1000 &
1#
#75000
0#
#76000
b111 "
b111 &
1#
#77000
0#
#78000
b110 "
b110 &
1#
#79000
0#
#80000
b101 "
b101 &
1#
#81000
0#
#82000
b100 "
b100 &
1#
#83000
0#
#84000
b11 "
b11 &
1#
#85000
0#
#86000
b10 "
b10 &
1#
#87000
0#
#88000
b1 "
b1 &
1#
#89000
0#
#90000
b0 "
b0 &
1#
#91000
0#
#92000
b10 !
b10 '
b1001 "
b1001 &
1#
#93000
0#
#94000
b1000 "
b1000 &
1#
#95000
0#
#96000
b111 "
b111 &
1#
#97000
0#
#98000
b110 "
b110 &
1#
#99000
0#
#100000
b101 "
b101 &
1#
#101000
0#
#102000
b100 "
b100 &
1#
#103000
0#
#104000
b11 "
b11 &
1#
#105000
0#
#106000
b10 "
b10 &
1#
#107000
0#
#108000
b1 "
b1 &
1#
#109000
0#
#110000
b0 "
b0 &
1#
#111000
0#
#112000
b1 !
b1 '
b1001 "
b1001 &
1#
#113000
0#
#114000
b1000 "
b1000 &
1#
#115000
0#
#116000
b111 "
b111 &
1#
#117000
0#
#118000
b110 "
b110 &
1#
#119000
0#
#120000
b101 "
b101 &
1#
#121000
0#
#122000
b100 "
b100 &
1#
#123000
0#
#124000
b11 "
b11 &
1#
#125000
0#
#126000
b10 "
b10 &
1#
#127000
0#
#128000
b1 "
b1 &
1#
#129000
0#
#130000
b0 "
b0 &
1#
#131000
0#
#132000
b0 !
b0 '
b1001 "
b1001 &
1#
#133000
0#
#134000
b1000 "
b1000 &
1#
#135000
0#
#136000
b111 "
b111 &
1#
#137000
0#
#138000
b110 "
b110 &
1#
#139000
0#
#140000
b101 "
b101 &
1#
#141000
0#
#142000
b100 "
b100 &
1#
#143000
0#
#144000
b11 "
b11 &
1#
#145000
0#
#146000
b10 "
b10 &
1#
#147000
0#
#148000
b1 "
b1 &
1#
#149000
0#
#150000
b0 "
b0 &
1#
