Laboratorios/Ejemplo implementacion/Wmult_FSM.v
`timescale 1ns / 1ps
//////////////////////////////////////////////////////////////////////////////////
// Company: 
// Engineer: 
// 
// Create Date: 06.02.2022 19:51:12
// Design Name: 
// Module Name: Wmult_FSM
// Project Name: 
// Target Devices: 
// Tool Versions: 
// Description: 
// 
// Dependencies: 
// 
// Revision:
// Revision 0.01 - File Created
// Additional Comments:
// 
//////////////////////////////////////////////////////////////////////////////////


module Wmult_FSM(
    input clk,
    input start,
    input [7:0] RQ,
    output reg EM,
    output reg RA,
    output reg RRQ,
    output reg RRP,
    output reg busy
    );
    
    parameter Espera  = 2'b00;
    parameter Calcula = 2'b01;
    parameter Imprime = 2'b10;

    reg [1:0] presente = Espera; // Registro de Estado - Valor inicial
    reg [1:0] futuro;            // Entrada del registro de Estado

    // Registro de estado 
    always @(posedge clk)
        presente <= futuro;

    // Lógica del estado siguiente
    always @(presente, start, RQ)
        case (presente)
            Espera :
                if(start)
                    futuro <= Calcula;
                else
                    futuro <= Espera;
            Calcula:
                if(RQ[7:1]==7'b0000000)
                    futuro <= Imprime;
                else
                    futuro <= Calcula;
            Imprime:
                futuro <= Espera;
            default:
                futuro <= Espera;
        endcase
    
    // Lógica de salida
    always @(presente)
        case (presente)
            Espera : begin
                EM <= 1'b0;
                RA <= 1'b1;
                RRQ <= 1'b1;
                RRP <= 1'b1;
                busy <= 1'b0;
            end
            Calcula: begin
                EM <= 1'b0;
                RA <= 1'b0;
                RRQ <= 1'b0;
                RRP <= 1'b0;
                busy <= 1'b1;
            end
            Imprime: begin
                EM <= 1'b1;
                RA <= 1'b1;
                RRQ <= 1'b1;
                RRP <= 1'b1;
                busy <= 1'b1;
            end
            default: begin
                EM <= 1'b0;
                RA <= 1'b1;
                RRQ <= 1'b1;
                RRP <= 1'b1;
                busy <= 1'b0;
            end
        endcase
    
endmodule

Laboratorios/Ejemplo implementacion/Wmult_DP.v
`timescale 1ns / 1ps
//////////////////////////////////////////////////////////////////////////////////
// Company: 
// Engineer: 
// 
// Create Date: 06.02.2022 19:51:12
// Design Name: 
// Module Name: Wmult_DP
// Project Name: 
// Target Devices: 
// Tool Versions: 
// Description: 
// 
// Dependencies: 
// 
// Revision:
// Revision 0.01 - File Created
// Additional Comments:
// 
//////////////////////////////////////////////////////////////////////////////////


module Wmult_DP(
    input clk,
    input [7:0] P,
    input [7:0] Q,
    output reg [15:0] M,
    input EM,
    input RA,
    input RRQ,
    input RRP,
    output reg [7:0] RQ
    );
    
    //reg  [15:0] M;
    wire [15:0] nextM;
    reg  [15:0] A;
    wire [15:0] nextA;
    //reg  [7:0] RQ;
    wire [7:0] nextRQ;
    reg  [15:0] RP;
    wire [15:0] nextRP;
    
    // Registro M
    always @(posedge clk)
        M <= nextM;
    // Parte combinacional de M
    assign nextM = (EM)?A:M;
    
    // Registro A
    always @(posedge clk)
        A <= nextA;
    // Parte combinacional de A
    assign nextA = (RA)? 16'd0 : A+( RP & {16{RQ[0]}} );
    
    // Registro RQ
    always @(posedge clk)
        RQ <= nextRQ;
    // Parte combinacional de RQ
    assign nextRQ = (RRQ)? Q : {1'b0, RQ[7:1]};
    
    // Registro RP
    always @(posedge clk)
        RP <= nextRP;
    // Parte combinacional de RP
    assign nextRP = (RRP)? {8'b0, P} : {RP[14:0], 1'b0};
    
endmodule

Laboratorios/Ejemplo implementacion/Wmult_top.v
`timescale 1ns / 1ps
//////////////////////////////////////////////////////////////////////////////////
// Company: 
// Engineer: 
// 
// Create Date: 06.02.2022 19:51:12
// Design Name: 
// Module Name: Wmult_top
// Project Name: 
// Target Devices: 
// Tool Versions: 
// Description: 
// 
// Dependencies: 
// 
// Revision:
// Revision 0.01 - File Created
// Additional Comments:
// 
//////////////////////////////////////////////////////////////////////////////////


module Wmult_top(
    input clk,
    input start,
    output busy,
    input [7:0] P,
    input [7:0] Q,
    output [15:0] M
    );
    
    wire EM, RA, RRQ, RRP;
    wire [7:0] RQ;
    
    Wmult_DP Datapath (
        .clk(clk),
        .P(P),
        .Q(Q),
        .M(M),
        .EM(EM),
        .RA(RA),
        .RRQ(RRQ),
        .RRP(RRP),
        .RQ(RQ)
        );

    Wmult_FSM Control_Unit (
            .clk(clk),
            .start(start),
            .RQ(RQ),
            .EM(EM),
            .RA(RA),
            .RRQ(RRQ),
            .RRP(RRP),
            .busy(busy)
            );
    
endmodule

Laboratorios/Ejemplo implementacion/Wmult_top_TB.v
`timescale 1ns / 1ps
//////////////////////////////////////////////////////////////////////////////////
// Company: 
// Engineer: 
// 
// Create Date: 07.02.2022 04:29:41
// Design Name: 
// Module Name: Wmult_top_TB
// Project Name: 
// Target Devices: 
// Tool Versions: 
// Description: 
// 
// Dependencies: 
// 
// Revision:
// Revision 0.01 - File Created
// Additional Comments:
// 
//////////////////////////////////////////////////////////////////////////////////


module Wmult_top_TB( );

    reg clk = 1'b0; 
    reg start;
    wire busy;
    reg [7:0] P; 
    reg [7:0] Q;
    wire [15:0] M;

Wmult_top UUT (
    .clk(clk),
    .start(start),
    .busy(busy),
    .P(P),
    .Q(Q),
    .M(M)
    );
    
    // clk generation
    always #5 clk = ~clk;
    
    initial
    begin
        P <= 8'd0;
        Q <= 8'd0;
        start <= 1'b0;
        #100

        P <= 8'd2;
        Q <= 8'd3;
        start <= 1'b0;
        #10
        start <= 1'b1;
        #10
        start <= 1'b0;
        #90
        
        P <= 8'd5;
        Q <= 8'd63;
        start <= 1'b0;
        #10
        start <= 1'b1;
        #10
        start <= 1'b0;
        #90
        
        P <= 8'd0;
        Q <= 8'd255;
        start <= 1'b0;
        #10
        start <= 1'b1;
        #10
        start <= 1'b0;
        #90
        
        P <= 8'd1;
        Q <= 8'd255;
        start <= 1'b0;
        #10
        start <= 1'b1;
        #10
        start <= 1'b0;
        #90
        
        P <= 8'd255;
        Q <= 8'd0;
        start <= 1'b0;
        #10
        start <= 1'b1;
        #10
        start <= 1'b0;
        #90
        
        P <= 8'd255;
        Q <= 8'd1;
        start <= 1'b0;
        #10
        start <= 1'b1;
        #10
        start <= 1'b0;
        #90
        
        P <= 8'd255;
        Q <= 8'd255;
        start <= 1'b0;
        #10
        start <= 1'b1;
        #10
        start <= 1'b0;
        #120
        
        $finish();
    end
    initial begin
	$dumpfile("prueba.vcd");
    $dumpvars;
    end
endmodule

Laboratorios/Ejemplo implementacion/prueba.vcd
$date
	Wed Feb 16 23:51:53 2022
$end
$version
	Icarus Verilog
$end
$timescale
	1ps
$end
$scope module Wmult_top_TB $end
$var wire 1 ! busy $end
$var wire 16 " M [15:0] $end
$var reg 8 # P [7:0] $end
$var reg 8 $ Q [7:0] $end
$var reg 1 % clk $end
$var reg 1 & start $end
$scope module UUT $end
$var wire 8 ' P [7:0] $end
$var wire 8 ( Q [7:0] $end
$var wire 1 % clk $end
$var wire 1 & start $end
$var wire 1 ! busy $end
$var wire 1 ) RRQ $end
$var wire 1 * RRP $end
$var wire 8 + RQ [7:0] $end
$var wire 1 , RA $end
$var wire 16 - M [15:0] $end
$var wire 1 . EM $end
$scope module Control_Unit $end
$var wire 1 % clk $end
$var wire 1 & start $end
$var wire 8 / RQ [7:0] $end
$var reg 1 . EM $end
$var reg 1 , RA $end
$var reg 1 * RRP $end
$var reg 1 ) RRQ $end
$var reg 1 ! busy $end
$var reg 2 0 futuro [1:0] $end
$var reg 2 1 presente [1:0] $end
$upscope $end
$scope module Datapath $end
$var wire 1 . EM $end
$var wire 8 2 P [7:0] $end
$var wire 8 3 Q [7:0] $end
$var wire 1 , RA $end
$var wire 1 * RRP $end
$var wire 1 ) RRQ $end
$var wire 1 % clk $end
$var wire 8 4 nextRQ [7:0] $end
$var wire 16 5 nextRP [15:0] $end
$var wire 16 6 nextM [15:0] $end
$var wire 16 7 nextA [15:0] $end
$var reg 16 8 A [15:0] $end
$var reg 16 9 M [15:0] $end
$var reg 16 : RP [15:0] $end
$var reg 8 ; RQ [7:0] $end
$upscope $end
$upscope $end
$upscope $end
$enddefinitions $end
#0
$dumpvars
bx ;
bx :
bx 9
bx 8
b0 7
bx 6
b0 5
b0 4
b0 3
b0 2
b0 1
b0 0
bx /
0.
bx -
1,
bx +
1*
1)
b0 (
b0 '
0&
0%
b0 $
b0 #
bx "
0!
$end
#5000
b0 8
b0 +
b0 /
b0 ;
b0 :
1%
#10000
0%
#15000
1%
#20000
0%
#25000
1%
#30000
0%
#35000
1%
#40000
0%
#45000
1%
#50000
0%
#55000
1%
#60000
0%
#65000
1%
#70000
0%
#75000
1%
#80000
0%
#85000
1%
#90000
0%
#95000
1%
#100000
b11 4
b10 5
b11 $
b11 (
b11 3
b10 #
b10 '
b10 2
0%
#105000
b11 +
b11 /
b11 ;
b10 :
1%
#110000
b1 0
1&
0%
#115000
b100 5
b1 4
b10 7
1!
0*
0)
0,
b1 1
1%
#120000
0&
0%
#125000
b10 0
b0 4
b1000 5
b110 7
b10 8
b1 +
b1 /
b1 ;
b100 :
1%
#130000
0%
#135000
b11 4
b110 6
1*
1)
1,
1.
b0 0
b10 5
b0 7
b10 1
b1000 :
b0 +
b0 /
b0 ;
b110 8
1%
#140000
0%
#145000
0!
0.
b110 6
b110 "
b110 -
b110 9
b0 8
b11 +
b11 /
b11 ;
b10 :
b0 1
1%
#150000
0%
#155000
1%
#160000
0%
#165000
1%
#170000
0%
#175000
1%
#180000
0%
#185000
1%
#190000
0%
#195000
1%
#200000
0%
#205000
1%
#210000
b111111 4
b101 5
b111111 $
b111111 (
b111111 3
b101 #
b101 '
b101 2
0%
#215000
b101 :
b111111 +
b111111 /
b111111 ;
1%
#220000
b1 0
1&
0%
#225000
b1010 5
b11111 4
b101 7
1!
0*
0)
0,
b1 1
1%
#230000
0&
0%
#235000
b10100 5
b1111 4
b1111 7
b1010 :
b11111 +
b11111 /
b11111 ;
b101 8
1%
#240000
0%
#245000
b111 4
b101000 5
b100011 7
b1111 8
b1111 +
b1111 /
b1111 ;
b10100 :
1%
#250000
0%
#255000
b1010000 5
b11 4
b1001011 7
b101000 :
b111 +
b111 /
b111 ;
b100011 8
1%
#260000
0%
#265000
b1 4
b10100000 5
b10011011 7
b1001011 8
b11 +
b11 /
b11 ;
b1010000 :
1%
#270000
0%
#275000
b10 0
b101000000 5
b0 4
b100111011 7
b10100000 :
b1 +
b1 /
b1 ;
b10011011 8
1%
#280000
0%
#285000
b111111 4
b100111011 6
1*
1)
1,
1.
b0 0
b101 5
b0 7
b100111011 8
b0 +
b0 /
b0 ;
b101000000 :
b10 1
1%
#290000
0%
#295000
0!
0.
b100111011 6
b0 1
b101 :
b111111 +
b111111 /
b111111 ;
b0 8
b100111011 "
b100111011 -
b100111011 9
1%
#300000
0%
#305000
1%
#310000
0%
#315000
1%
#320000
b11111111 4
b0 5
b11111111 $
b11111111 (
b11111111 3
b0 #
b0 '
b0 2
0%
#325000
b11111111 +
b11111111 /
b11111111 ;
b0 :
1%
#330000
b1 0
1&
0%
#335000
b1111111 4
1!
0*
0)
0,
b1 1
1%
#340000
0&
0%
#345000
b111111 4
b1111111 +
b1111111 /
b1111111 ;
1%
#350000
0%
#355000
b11111 4
b111111 +
b111111 /
b111111 ;
1%
#360000
0%
#365000
b1111 4
b11111 +
b11111 /
b11111 ;
1%
#370000
0%
#375000
b111 4
b1111 +
b1111 /
b1111 ;
1%
#380000
0%
#385000
b11 4
b111 +
b111 /
b111 ;
1%
#390000
0%
#395000
b1 4
b11 +
b11 /
b11 ;
1%
#400000
0%
#405000
b10 0
b0 4
b1 +
b1 /
b1 ;
1%
#410000
0%
#415000
b11111111 4
b0 6
1*
1)
1,
1.
b0 0
b10 1
b0 +
b0 /
b0 ;
1%
#420000
0%
#425000
0!
0.
b0 "
b0 -
b0 9
b11111111 +
b11111111 /
b11111111 ;
b0 1
1%
#430000
b1 5
b1 #
b1 '
b1 2
0%
#435000
b1 :
1%
#440000
b1 0
1&
0%
#445000
b10 5
b1111111 4
b1 7
1!
0*
0)
0,
b1 1
1%
#450000
0&
0%
#455000
b100 5
b111111 4
b11 7
b10 :
b1111111 +
b1111111 /
b1111111 ;
b1 8
1%
#460000
0%
#465000
b11111 4
b1000 5
b111 7
b11 8
b111111 +
b111111 /
b111111 ;
b100 :
1%
#470000
0%
#475000
b10000 5
b1111 4
b1111 7
b1000 :
b11111 +
b11111 /
b11111 ;
b111 8
1%
#480000
0%
#485000
b111 4
b100000 5
b11111 7
b1111 8
b1111 +
b1111 /
b1111 ;
b10000 :
1%
#490000
0%
#495000
b1000000 5
b11 4
b111111 7
b100000 :
b111 +
b111 /
b111 ;
b11111 8
1%
#500000
0%
#505000
b1 4
b10000000 5
b1111111 7
b111111 8
b11 +
b11 /
b11 ;
b1000000 :
1%
#510000
0%
#515000
b10 0
b100000000 5
b0 4
b11111111 7
b10000000 :
b1 +
b1 /
b1 ;
b1111111 8
1%
#520000
0%
#525000
b11111111 4
b11111111 6
1*
1)
1,
1.
b0 0
b1 5
b0 7
b11111111 8
b0 +
b0 /
b0 ;
b100000000 :
b10 1
1%
#530000
0%
#535000
0!
0.
b11111111 6
b0 1
b1 :
b11111111 +
b11111111 /
b11111111 ;
b0 8
b11111111 "
b11111111 -
b11111111 9
1%
#540000
b0 4
b11111111 5
b0 $
b0 (
b0 3
b11111111 #
b11111111 '
b11111111 2
0%
#545000
b0 +
b0 /
b0 ;
b11111111 :
1%
#550000
b1 0
1&
0%
#555000
b111111110 5
1!
0*
0)
0,
b10 0
b1 1
1%
#560000
0&
0%
#565000
b0 6
1*
1)
1,
1.
b0 0
b11111111 5
b111111110 :
b10 1
1%
#570000
0%
#575000
0!
0.
b0 1
b11111111 :
b0 "
b0 -
b0 9
1%
#580000
0%
#585000
1%
#590000
0%
#595000
1%
#600000
0%
#605000
1%
#610000
0%
#615000
1%
#620000
0%
#625000
1%
#630000
0%
#635000
1%
#640000
0%
#645000
1%
#650000
b1 4
b1 $
b1 (
b1 3
0%
#655000
b1 +
b1 /
b1 ;
1%
#660000
b1 0
1&
0%
#665000
b111111110 5
b0 4
b11111111 7
1!
0*
0)
0,
b10 0
b1 1
1%
#670000
0&
0%
#675000
b1 4
b11111111 6
1*
1)
1,
1.
b0 0
b11111111 5
b0 7
b10 1
b111111110 :
b0 +
b0 /
b0 ;
b11111111 8
1%
#680000
0%
#685000
0!
0.
b11111111 6
b11111111 "
b11111111 -
b11111111 9
b0 8
b1 +
b1 /
b1 ;
b11111111 :
b0 1
1%
#690000
0%
#695000
1%
#700000
0%
#705000
1%
#710000
0%
#715000
1%
#720000
0%
#725000
1%
#730000
0%
#735000
1%
#740000
0%
#745000
1%
#750000
0%
#755000
1%
#760000
b11111111 4
b11111111 $
b11111111 (
b11111111 3
0%
#765000
b11111111 +
b11111111 /
b11111111 ;
1%
#770000
b1 0
1&
0%
#775000
b111111110 5
b1111111 4
b11111111 7
1!
0*
0)
0,
b1 1
1%
#780000
0&
0%
#785000
b111111 4
b1111111100 5
b1011111101 7
b11111111 8
b1111111 +
b1111111 /
b1111111 ;
b111111110 :
1%
#790000
0%
#795000
b11111111000 5
b11111 4
b11011111001 7
b1111111100 :
b111111 +
b111111 /
b111111 ;
b1011111101 8
1%
#800000
0%
#805000
b1111 4
b111111110000 5
b111011110001 7
b11011111001 8
b11111 +
b11111 /
b11111 ;
b11111111000 :
1%
#810000
0%
#815000
b1111111100000 5
b111 4
b1111011100001 7
b111111110000 :
b1111 +
b1111 /
b1111 ;
b111011110001 8
1%
#820000
0%
#825000
b11 4
b11111111000000 5
b11111011000001 7
b1111011100001 8
b111 +
b111 /
b111 ;
b1111111100000 :
1%
#830000
0%
#835000
b111111110000000 5
b1 4
b111111010000001 7
b11111111000000 :
b11 +
b11 /
b11 ;
b11111011000001 8
1%
#840000
0%
#845000
b10 0
b0 4
b1111111100000000 5
b1111111000000001 7
b111111010000001 8
b1 +
b1 /
b1 ;
b111111110000000 :
1%
#850000
0%
#855000
b11111111 4
b1111111000000001 6
1*
1)
1,
1.
b0 0
b11111111 5
b0 7
b10 1
b1111111100000000 :
b0 +
b0 /
b0 ;
b1111111000000001 8
1%
#860000
0%
#865000
0!
0.
b1111111000000001 6
b1111111000000001 "
b1111111000000001 -
b1111111000000001 9
b0 8
b11111111 +
b11111111 /
b11111111 ;
b11111111 :
b0 1
1%
