Laboratorios/punto5/nosimp/punto5nosimp_t.v
module punto5nosimp_t(
//entradas y salidas
//modo tipo ancho nombre
 input A,B,C,
 output F
);
assign F=(A & ~B & C)|(A & ~B & ~C)|(A & B & C)|(~A & ~B & C);
endmodule

Laboratorios/punto5/nosimp/punto5nosimp_t_tb.v
`timescale 1ns / 10 ps
module punto5nosimp_t_tb();
//********************************
//declaracion de variables para conexion
 reg [2:0] in;
 wire outF;
//********************************
//conexion del circuito
punto5nosimp_t EJR2(
.A(in[2]),
.B(in[1]),
.C(in[0]),
.F(outF)
);
//*********************************
/*estimulos
initial begin
  inA=1'b0; inB=1'b0; inC=1'b0;  #20;
  inA=1'b0; inB=1'b0; inC=1'b1;  #20;
  inA=1'b0; inB=1'b1; inC=1'b0;  #20;
  inA=1'b0; inB=1'b1; inC=1'b1;  #20;
  inA=1'b1; inB=1'b0; inC=1'b0;  #20;
  inA=1'b1; inB=1'b0; inC=1'b1;  #20;
  inA=1'b1; inB=1'b1; inC=1'b0;  #20;
  inA=1'b1; inB=1'b1; inC=1'b1;  #20;
  $finish;
end
*/

initial begin
     in=0;              #10; //espera
repeat (7) begin
     in=in+1;       #10;
	 end
	 $finish; //termina la simulacion
end

//************************************
//mostrar resultados con gtkwave
initial begin
  $dumpfile("ARCHIVO.vcd");
  $dumpvars;
end
//**********************************
//mostrar resultados en consola
initial begin
$display("|-------|---|");
$display("|  ABC  | F |");
$display("|-------|---|");
$monitor("|  %b  | %b |",in,outF);
end

endmodule

Laboratorios/punto5/nosimp/ARCHIVO.vcd
$date
	Thu Aug 19 14:06:47 2021
$end
$version
	Icarus Verilog
$end
$timescale
	10ps
$end
$scope module punto5nosimp_t_tb $end
$var wire 1 ! outF $end
$var reg 3 " in [2:0] $end
$scope module EJR2 $end
$var wire 1 # A $end
$var wire 1 $ B $end
$var wire 1 % C $end
$var wire 1 ! F $end
$upscope $end
$upscope $end
$enddefinitions $end
#0
$dumpvars
0%
0$
0#
b0 "
0!
$end
#1000
1!
1%
b1 "
#2000
0!
1$
0%
b10 "
#3000
1%
b11 "
#4000
1!
1#
0$
0%
b100 "
#5000
1%
b101 "
#6000
0!
1$
0%
b110 "
#7000
1!
1%
b111 "
