Laboratorios/punto5/simp/punto5simp_t.v
module punto5simp_t(
//entradas y salidas
//modo tipo ancho nombre
 input A,B,C,
 output F
);
assign F=(A & ~B)|(~B & C)|(A & C);
endmodule

Laboratorios/punto5/simp/punto5simp_t_tb.v
`timescale 1ns / 10 ps
module punto5simp_t_tb();
//********************************
//declaracion de variables para conexion
 reg inA,inB,inC;
 wire outF;
//********************************
//conexion del circuito
punto5simp_t EJR(
.A(inA),
.B(inB),
.C(inC),
.F(outF)
);
//*********************************
//estimulos
initial begin
  inA=1'b0; inB=1'b0; inC=1'b0;  #20;
  inA=1'b0; inB=1'b0; inC=1'b1;  #20;
  inA=1'b0; inB=1'b1; inC=1'b0;  #20;
  inA=1'b0; inB=1'b1; inC=1'b1;  #20;
  inA=1'b1; inB=1'b0; inC=1'b0;  #20;
  inA=1'b1; inB=1'b0; inC=1'b1;  #20;
  inA=1'b1; inB=1'b1; inC=1'b0;  #20;
  inA=1'b1; inB=1'b1; inC=1'b1;  #20;
  $finish;
end
//************************************
//mostrar resultados con gtkwave
initial begin
  $dumpfile("ARCHIVO.vcd");
  $dumpvars;
end
//**********************************
//mostrar resultados en consola
initial begin
$display("-------|---");
$display(" A B C | F ");
$display("-------|---");
$monitor(" %b %b %b | %b",inA,inB,inC,outF);
end

endmodule

Laboratorios/punto5/simp/ARCHIVO.vcd
$date
	Thu Aug 12 07:22:31 2021
$end
$version
	Icarus Verilog
$end
$timescale
	10ps
$end
$scope module punto5simp_t_tb $end
$var wire 1 ! outF $end
$var reg 1 " inA $end
$var reg 1 # inB $end
$var reg 1 $ inC $end
$scope module EJR $end
$var wire 1 " A $end
$var wire 1 # B $end
$var wire 1 $ C $end
$var wire 1 ! F $end
$upscope $end
$upscope $end
$enddefinitions $end
#0
$dumpvars
0$
0#
0"
0!
$end
#2000
1!
1$
#4000
0!
0$
1#
#6000
1$
#8000
1!
0$
0#
1"
#10000
1$
#12000
0!
0$
1#
#14000
1!
1$
